romajiphonem/__init__.py
romajiphonem/api.py
romaji_phonem-0.2.0.dist-info/LICENSE
romaji_phonem-0.2.0.dist-info/METADATA
romaji_phonem-0.2.0.dist-info/WHEEL
romaji_phonem-0.2.0.dist-info/RECORD
