Metadata-Version: 2.1
Name: romaji-phonem
Version: 0.2.0
Summary: アルファベット列をローマ字読みする軽量 Python ライブラリ.
Home-page: https://github.com/takosavi/romaji-phonem
License: MIT
Author: もち (Mochi)
Author-email: mochi.takosavi@gmail.com
Requires-Python: >=3.9,<4.0
Classifier: Development Status :: 3 - Alpha
Classifier: Intended Audience :: Developers
Classifier: License :: OSI Approved :: MIT License
Classifier: Natural Language :: Japanese
Classifier: Programming Language :: Python :: 3
Classifier: Programming Language :: Python :: 3.9
Classifier: Programming Language :: Python :: 3.10
Classifier: Programming Language :: Python :: 3.11
Classifier: Programming Language :: Python :: 3.12
Classifier: Programming Language :: Python :: 3.13
Classifier: Topic :: Text Processing :: Linguistic
Project-URL: Repository, https://github.com/takosavi/romaji-phonem
